{
  "chains": [
    {
      "slug": "Ethereum",
      "name": "Ethereum",
      "tvlRank": 1,
      "tvl": 71830533738.5801,
      "protocolCount": 1656,
      "tokenSymbol": "ETH",
      "historyDays": 3028,
      "change30d": 0.008390620177990417,
      "lastUpdated": "2026-01-11"
    },
    {
      "slug": "Solana",
      "name": "Solana",
      "tvlRank": 2,
      "tvl": 8868056957.16797,
      "protocolCount": 341,
      "tokenSymbol": "SOL",
      "historyDays": 1760,
      "change30d": -0.009265406742278747,
      "lastUpdated": "2026-01-11"
    },
    {
      "slug": "Bitcoin",
      "name": "Bitcoin",
      "tvlRank": 3,
      "tvl": 6971991873.255012,
      "protocolCount": 156,
      "tokenSymbol": "BTC",
      "historyDays": 1757,
      "change30d": 0.042226126005500374,
      "lastUpdated": "2026-01-11"
    },
    {
      "slug": "Base",
      "name": "Base",
      "tvlRank": 5,
      "tvl": 4734279686.112284,
      "protocolCount": 690,
      "tokenSymbol": null,
      "historyDays": 941,
      "change30d": 0.032335616691224485,
      "lastUpdated": "2026-01-11"
    },
    {
      "slug": "Tron",
      "name": "Tron",
      "tvlRank": 6,
      "tvl": 4598991619.313437,
      "protocolCount": 93,
      "tokenSymbol": "TRON",
      "historyDays": 2109,
      "change30d": 0.009196840290880288,
      "lastUpdated": "2026-01-11"
    },
    {
      "slug": "Plasma",
      "name": "Plasma",
      "tvlRank": 7,
      "tvl": 3385297296.040654,
      "protocolCount": 57,
      "tokenSymbol": "XPL",
      "historyDays": 129,
      "change30d": 0.07663786386638853,
      "lastUpdated": "2026-01-11"
    },
    {
      "slug": "Arbitrum",
      "name": "Arbitrum",
      "tvlRank": 8,
      "tvl": 3048489173.4588833,
      "protocolCount": 941,
      "tokenSymbol": "ARB",
      "historyDays": 1682,
      "change30d": 0.01368859240725451,
      "lastUpdated": "2026-01-11"
    },
    {
      "slug": "Hyperliquid L1",
      "name": "Hyperliquid L1",
      "tvlRank": 9,
      "tvl": 1311141476.387063,
      "protocolCount": 113,
      "tokenSymbol": "HYPE",
      "historyDays": 458,
      "change30d": -0.18694458900724367,
      "lastUpdated": "2026-01-11"
    },
    {
      "slug": "Avalanche",
      "name": "Avalanche",
      "tvlRank": 10,
      "tvl": 1303123746.8389006,
      "protocolCount": 534,
      "tokenSymbol": "AVAX",
      "historyDays": 1803,
      "change30d": 0.005790764557364085,
      "lastUpdated": "2026-01-11"
    },
    {
      "slug": "Polygon",
      "name": "Polygon",
      "tvlRank": 11,
      "tvl": 1088403083.4853337,
      "protocolCount": 692,
      "tokenSymbol": "POL",
      "historyDays": 1920,
      "change30d": -0.08519850721443968,
      "lastUpdated": "2026-01-11"
    },
    {
      "slug": "Sui",
      "name": "Sui",
      "tvlRank": 12,
      "tvl": 1036206564.5723959,
      "protocolCount": 105,
      "tokenSymbol": "SUI",
      "historyDays": 981,
      "change30d": 0.12291157878218019,
      "lastUpdated": "2026-01-11"
    },
    {
      "slug": "Ink",
      "name": "Ink",
      "tvlRank": 14,
      "tvl": 541460045.6195127,
      "protocolCount": 20,
      "tokenSymbol": null,
      "historyDays": 389,
      "change30d": 0.3618627157536785,
      "lastUpdated": "2026-01-11"
    },
    {
      "slug": "Aptos",
      "name": "Aptos",
      "tvlRank": 15,
      "tvl": 441134266.55375904,
      "protocolCount": 89,
      "tokenSymbol": "APT",
      "historyDays": 1178,
      "change30d": -0.04044667426922952,
      "lastUpdated": "2026-01-11"
    },
    {
      "slug": "Cronos",
      "name": "Cronos",
      "tvlRank": 17,
      "tvl": 385235555.31175786,
      "protocolCount": 135,
      "tokenSymbol": "CRO",
      "historyDays": 1522,
      "change30d": -0.0044979901359352694,
      "lastUpdated": "2026-01-11"
    },
    {
      "slug": "Katana",
      "name": "Katana",
      "tvlRank": 18,
      "tvl": 379796380.46709096,
      "protocolCount": 21,
      "tokenSymbol": null,
      "historyDays": 234,
      "change30d": -0.11603078086524286,
      "lastUpdated": "2026-01-11"
    },
    {
      "slug": "Mantle",
      "name": "Mantle",
      "tvlRank": 19,
      "tvl": 330353131.41296834,
      "protocolCount": 135,
      "tokenSymbol": "MNT",
      "historyDays": 909,
      "change30d": -0.0649550315428774,
      "lastUpdated": "2026-01-11"
    },
    {
      "slug": "Starknet",
      "name": "Starknet",
      "tvlRank": 21,
      "tvl": 286238991.533162,
      "protocolCount": 52,
      "tokenSymbol": "STRK",
      "historyDays": 1130,
      "change30d": 0.2698742131803664,
      "lastUpdated": "2026-01-11"
    },
    {
      "slug": "Monad",
      "name": "Monad",
      "tvlRank": 22,
      "tvl": 279337610.0046895,
      "protocolCount": 67,
      "tokenSymbol": "MON",
      "historyDays": 54,
      "change30d": 0.427061535102733,
      "lastUpdated": "2026-01-11"
    },
    {
      "slug": "Flare",
      "name": "Flare",
      "tvlRank": 23,
      "tvl": 205548812.67456982,
      "protocolCount": 33,
      "tokenSymbol": "FLR",
      "historyDays": 1102,
      "change30d": 0.08370530015398274,
      "lastUpdated": "2026-01-11"
    },
    {
      "slug": "Scroll",
      "name": "Scroll",
      "tvlRank": 25,
      "tvl": 199326982.24219292,
      "protocolCount": 136,
      "tokenSymbol": null,
      "historyDays": 823,
      "change30d": -0.004034692435928401,
      "lastUpdated": "2026-01-11"
    },
    {
      "slug": "Sei",
      "name": "Sei",
      "tvlRank": 26,
      "tvl": 198672196.0518606,
      "protocolCount": 68,
      "tokenSymbol": "SEI",
      "historyDays": 878,
      "change30d": -0.07718205981355049,
      "lastUpdated": "2026-01-11"
    },
    {
      "slug": "Stellar",
      "name": "Stellar",
      "tvlRank": 27,
      "tvl": 190352281.53938928,
      "protocolCount": 25,
      "tokenSymbol": "XLM",
      "historyDays": 1513,
      "change30d": 0.06917649865169168,
      "lastUpdated": "2026-01-11"
    },
    {
      "slug": "Cardano",
      "name": "Cardano",
      "tvlRank": 29,
      "tvl": 182427633.24271768,
      "protocolCount": 78,
      "tokenSymbol": "ADA",
      "historyDays": 1470,
      "change30d": -0.03641094126680238,
      "lastUpdated": "2026-01-11"
    },
    {
      "slug": "Linea",
      "name": "Linea",
      "tvlRank": 30,
      "tvl": 179367065.66419554,
      "protocolCount": 159,
      "tokenSymbol": "LINEA",
      "historyDays": 907,
      "change30d": -0.28773152953549347,
      "lastUpdated": "2026-01-11"
    },
    {
      "slug": "Berachain",
      "name": "Berachain",
      "tvlRank": 31,
      "tvl": 173269934.62637827,
      "protocolCount": 95,
      "tokenSymbol": "BERA",
      "historyDays": 461,
      "change30d": -0.372177313318574,
      "lastUpdated": "2026-01-11"
    },
    {
      "slug": "Near",
      "name": "Near",
      "tvlRank": 35,
      "tvl": 142911231.25864303,
      "protocolCount": 43,
      "tokenSymbol": "NEAR",
      "historyDays": 1604,
      "change30d": -0.08584158223013098,
      "lastUpdated": "2026-01-11"
    },
    {
      "slug": "Stacks",
      "name": "Stacks",
      "tvlRank": 37,
      "tvl": 129057192.96993762,
      "protocolCount": 17,
      "tokenSymbol": "STX",
      "historyDays": 1490,
      "change30d": 0.04114680531199394,
      "lastUpdated": "2026-01-11"
    },
    {
      "slug": "Unichain",
      "name": "Unichain",
      "tvlRank": 38,
      "tvl": 99756642.02681367,
      "protocolCount": 56,
      "tokenSymbol": "-",
      "historyDays": 409,
      "change30d": -0.21427535511306298,
      "lastUpdated": "2026-01-11"
    },
    {
      "slug": "TON",
      "name": "TON",
      "tvlRank": 39,
      "tvl": 86327329.00094791,
      "protocolCount": 85,
      "tokenSymbol": "TON",
      "historyDays": 1132,
      "change30d": -0.013264479512790106,
      "lastUpdated": "2026-01-11"
    },
    {
      "slug": "Mixin",
      "name": "Mixin",
      "tvlRank": 40,
      "tvl": 86286285.21590245,
      "protocolCount": 10,
      "tokenSymbol": "XIN",
      "historyDays": 1502,
      "change30d": -0.01601611560605872,
      "lastUpdated": "2026-01-11"
    }
  ],
  "generatedAt": "2026-01-11T12:04:37.351Z"
}